LICENSE
README.md
setup.py
./src/zcrypto.c
./src/zcrypto_impl.c
helper/__init__.py
helper/helper.py
py_zcrypto.egg-info/PKG-INFO
py_zcrypto.egg-info/SOURCES.txt
py_zcrypto.egg-info/dependency_links.txt
py_zcrypto.egg-info/requires.txt
py_zcrypto.egg-info/top_level.txt
src/zcrypto.c
src/zcrypto.h
src/zcrypto_impl.c