Metadata-Version: 2.1
Name: py_zcrypto
Version: 1.0.2
Summary: Python interface for accessing RACF Keyrings and key databases on z/OS
Author: IBM
License: License :: OSI Approved :: Apache Software License
Project-URL: Source Code, https://github.com/IBM/py-zcrypto/
License-File: LICENSE
Requires-Dist: pyopenssl<=21.0.0
